exchange_rate_mcp/__init__.py
exchange_rate_mcp/server.py
exchange_rate_mcp/tools/csv_tools.py
exchange_rate_mcp/tools/extract_data.py
exchange_rate_mcp-0.1.0.dist-info/METADATA
exchange_rate_mcp-0.1.0.dist-info/WHEEL
exchange_rate_mcp-0.1.0.dist-info/entry_points.txt
exchange_rate_mcp-0.1.0.dist-info/RECORD
