Metadata-Version: 2.4
Name: exchange-rate-mcp
Version: 0.1.0
Summary: get exchange rate
Author-email: jay <googcheng@qq.com>
Requires-Python: >=3.11.8
Requires-Dist: firecrawl>=2.15.0
Requires-Dist: mcp[cli]>=1.10.1
